test_publish_pkg/__init__.py
test_publish_pkg/test_publish.py
test_publish_proj_with_uv-0.1.0.dist-info/METADATA
test_publish_proj_with_uv-0.1.0.dist-info/WHEEL
test_publish_proj_with_uv-0.1.0.dist-info/top_level.txt
test_publish_proj_with_uv-0.1.0.dist-info/RECORD
