Metadata-Version: 2.4
Name: test-publish-proj-with-uv
Version: 0.1.0
Summary: Add your description here,yangq
Requires-Python: >=3.9
Requires-Dist: dotenv>=0.9.9
Requires-Dist: requests>=2.32.4
